[
  {
    "systemSymbol": "X1-MC84",
    "symbol": "X1-MC84-60260A",
    "type": "PLANET",
    "x": 34,
    "y": -27,
    "orbitals": [],
    "traits": [
      {
        "symbol": "VOLCANIC",
        "name": "Volcanic",
        "description": "A volatile world marked by intense volcanic activity, creating a hazardous environment with the potential for valuable resource extraction, such as rare metals and geothermal energy."
      }
    ]
  },
  {
    "systemSymbol": "X1-MC84",
    "symbol": "X1-MC84-70071B",
    "type": "PLANET",
    "x": -51,
    "y": -22,
    "orbitals": [
      {
        "symbol": "X1-MC84-81562A"
      },
      {
        "symbol": "X1-MC84-07613A"
      }
    ],
    "traits": [
      {
        "symbol": "FROZEN",
        "name": "Frozen",
        "description": "An ice-covered world with frigid temperatures, providing unique research opportunities and resources such as ice water, ammonia ice, and other frozen compounds."
      }
    ]
  },
  {
    "systemSymbol": "X1-MC84",
    "symbol": "X1-MC84-81562A",
    "type": "MOON",
    "x": -51,
    "y": -22,
    "orbitals": [],
    "traits": [
      {
        "symbol": "JUNGLE",
        "name": "Jungle",
        "description": "A lush, tropical world with dense vegetation and a thriving ecosystem, offering a wealth of resources and unique opportunities for research and exploration."
      }
    ]
  },
  {
    "systemSymbol": "X1-MC84",
    "symbol": "X1-MC84-07613A",
    "type": "MOON",
    "x": -51,
    "y": -22,
    "orbitals": [],
    "traits": [
      {
        "symbol": "BARREN",
        "name": "Barren",
        "description": "A desolate world with little to no vegetation or water, presenting unique challenges for habitation and resource extraction."
      }
    ]
  },
  {
    "systemSymbol": "X1-MC84",
    "symbol": "X1-MC84-82064Z",
    "type": "PLANET",
    "x": 25,
    "y": 76,
    "orbitals": [
      {
        "symbol": "X1-MC84-71935A"
      }
    ],
    "traits": [
      {
        "symbol": "OCEAN",
        "name": "Ocean",
        "description": "A world dominated by vast, interconnected bodies of water, presenting unique challenges for habitation and resource extraction while supporting a diverse array of marine life."
      },
      {
        "symbol": "SPRAWLING_CITIES",
        "name": "Sprawling Cities",
        "description": "Expansive urban centers that stretch across the landscape, boasting advanced infrastructure and diverse populations."
      },
      {
        "symbol": "BUREAUCRATIC",
        "name": "Bureaucratic",
        "description": "A waypoint governed by complex regulations, red tape, and layers of administration, often leading to inefficiencies and frustration."
      },
      {
        "symbol": "INDUSTRIAL",
        "name": "Industrial",
        "description": "A waypoint dominated by factories, refineries, and other heavy industries, often accompanied by pollution and a bustling workforce."
      },
      {
        "symbol": "MARKETPLACE",
        "name": "Marketplace",
        "description": "A thriving center of commerce where traders from across the galaxy gather to buy, sell, and exchange goods."
      }
    ],
    "faction": {
      "symbol": "OBSIDIAN"
    }
  },
  {
    "systemSymbol": "X1-MC84",
    "symbol": "X1-MC84-71935A",
    "type": "MOON",
    "x": 25,
    "y": 76,
    "orbitals": [],
    "traits": [
      {
        "symbol": "JUNGLE",
        "name": "Jungle",
        "description": "A lush, tropical world with dense vegetation and a thriving ecosystem, offering a wealth of resources and unique opportunities for research and exploration."
      },
      {
        "symbol": "SPRAWLING_CITIES",
        "name": "Sprawling Cities",
        "description": "Expansive urban centers that stretch across the landscape, boasting advanced infrastructure and diverse populations."
      },
      {
        "symbol": "INDUSTRIAL",
        "name": "Industrial",
        "description": "A waypoint dominated by factories, refineries, and other heavy industries, often accompanied by pollution and a bustling workforce."
      }
    ],
    "faction": {
      "symbol": "OBSIDIAN"
    }
  }
]